streamable_server_1113/__init__.py
streamable_server_1113/main.py
streamable_server_1113-0.1.0.dist-info/WHEEL
streamable_server_1113-0.1.0.dist-info/entry_points.txt
streamable_server_1113-0.1.0.dist-info/METADATA
streamable_server_1113-0.1.0.dist-info/RECORD
