Metadata-Version: 2.3
Name: streamable-server-1113
Version: 0.1.0
Summary: Add your description here
Author: liuqw
Author-email: liuqw <liuqw@cn.ibm.com>
Requires-Dist: fastapi>=0.121.1
Requires-Dist: requests>=2.32.5
Requires-Dist: uvicorn>=0.38.0
Requires-Python: >=3.13
